Lumina/__init__.py
Lumina/colors.py
Lumina/lumina.py
Lumina/zone_creator.py
lumina-1.0.5.dist-info/METADATA
lumina-1.0.5.dist-info/WHEEL
lumina-1.0.5.dist-info/top_level.txt
lumina-1.0.5.dist-info/RECORD
