Metadata-Version: 2.1
Name: lumina
Version: 1.0.5
Summary: Customize your object detection bounding boxes and filter the tracking zones with Lumina
Author: Souvik Saha
Author-email: ssouvik.191@gmail.com
Keywords: machine_learning,development,data_augmentations
Classifier: Intended Audience :: Developers
Classifier: Operating System :: OS Independent
Classifier: Programming Language :: Python
Classifier: Programming Language :: Python :: 3.7
Classifier: License :: OSI Approved :: MIT License
Requires-Python: >=3.7
Requires-Dist: numpy
Requires-Dist: opencv-contrib-python (==4.7.0.72)
Requires-Dist: opencv-python (==4.7.0.72)
Requires-Dist: twine (==4.0.2)
